SmjaAi
